pb_analyzer/__init__.py
pb_analyzer/base_analyzer.py
pb_analyzer/const.py
pb_analyzer/power_bi_public_report_analyzer.py
pb_analyzer/power_bi_shared_reports_analyzer.py
pb_analyzer/utils.py
power_bi_analyzer-1.1.0.dist-info/LICENSE
power_bi_analyzer-1.1.0.dist-info/METADATA
power_bi_analyzer-1.1.0.dist-info/WHEEL
power_bi_analyzer-1.1.0.dist-info/entry_points.txt
power_bi_analyzer-1.1.0.dist-info/top_level.txt
power_bi_analyzer-1.1.0.dist-info/RECORD
