Metadata-Version: 2.1
Name: power-bi-analyzer
Version: 1.1.0
Summary: A package to analyze Power BI reports.
Home-page: https://github.com/Nokod/PBAnalyzer
Author: Nokod Security
Author-email: support@nokodsecurity.com
Classifier: Programming Language :: Python :: 3
Classifier: License :: OSI Approved :: MIT License
Classifier: Operating System :: OS Independent
Requires-Python: >=3.6
License-File: LICENSE
Requires-Dist: msal ~=1.28.0
Requires-Dist: requests >=2.32.0
Requires-Dist: setuptools ~=71.1.0
Requires-Dist: colorama ~=0.4.6
Requires-Dist: alive-progress ~=3.1.5
